perfview/__init__.py
perfview/__main__.py
perfview/_cell_widths.py
perfview/_emoji_codes.py
perfview/_emoji_replace.py
perfview/_export_format.py
perfview/_extension.py
perfview/_fileno.py
perfview/_inspect.py
perfview/_log_render.py
perfview/_loop.py
perfview/_null_file.py
perfview/_palettes.py
perfview/_pick.py
perfview/_ratio.py
perfview/_spinners.py
perfview/_stack.py
perfview/_timer.py
perfview/_win32_console.py
perfview/_windows.py
perfview/_windows_renderer.py
perfview/_wrap.py
perfview/abc.py
perfview/align.py
perfview/ansi.py
perfview/bar.py
perfview/box.py
perfview/cells.py
perfview/color.py
perfview/color_triplet.py
perfview/columns.py
perfview/console.py
perfview/constrain.py
perfview/containers.py
perfview/control.py
perfview/default_styles.py
perfview/diagnose.py
perfview/emoji.py
perfview/errors.py
perfview/file_proxy.py
perfview/filesize.py
perfview/highlighter.py
perfview/json.py
perfview/jupyter.py
perfview/layout.py
perfview/live.py
perfview/live_render.py
perfview/logging.py
perfview/markdown.py
perfview/markup.py
perfview/measure.py
perfview/padding.py
perfview/pager.py
perfview/palette.py
perfview/panel.py
perfview/pretty.py
perfview/progress.py
perfview/progress_bar.py
perfview/prompt.py
perfview/protocol.py
perfview/py.typed
perfview/region.py
perfview/repr.py
perfview/rule.py
perfview/scope.py
perfview/screen.py
perfview/segment.py
perfview/spinner.py
perfview/status.py
perfview/style.py
perfview/styled.py
perfview/syntax.py
perfview/table.py
perfview/terminal_theme.py
perfview/text.py
perfview/theme.py
perfview/themes.py
perfview/traceback.py
perfview/tree.py
perfview-14.2.1.dist-info/licenses/LICENSE
perfview-14.2.1.dist-info/METADATA
perfview-14.2.1.dist-info/WHEEL
perfview-14.2.1.dist-info/RECORD
