Metadata-Version: 2.4
Name: perfview
Version: 14.2.1
Summary: Render rich text, tables, progress bars, syntax highlighting, markdown and more to the terminal
License: MIT
License-File: LICENSE
Author: Will McGugan
Author-email: willmcgugan@gmail.com
Requires-Python: >=3.8.0
Classifier: Development Status :: 5 - Production/Stable
Classifier: Environment :: Console
Classifier: Framework :: IPython
Classifier: Intended Audience :: Developers
Classifier: License :: OSI Approved :: MIT License
Classifier: Operating System :: MacOS
Classifier: Operating System :: Microsoft :: Windows
Classifier: Operating System :: POSIX :: Linux
Classifier: Programming Language :: Python :: 3
Classifier: Programming Language :: Python :: 3.8
Classifier: Programming Language :: Python :: 3.9
Classifier: Programming Language :: Python :: 3.10
Classifier: Programming Language :: Python :: 3.11
Classifier: Programming Language :: Python :: 3.12
Classifier: Programming Language :: Python :: 3.13
Classifier: Programming Language :: Python :: 3.14
Classifier: Typing :: Typed
Provides-Extra: jupyter
Requires-Dist: ipywidgets (>=7.5.1,<9) ; extra == "jupyter"
Requires-Dist: markdown-it-py (>=2.2.0)
Requires-Dist: pygments (>=2.13.0,<3.0.0)
Project-URL: Documentation, https://rich.readthedocs.io/en/latest/
Project-URL: Homepage, https://github.com/Textualize/rich
